{
  "text":
  {
    "start": "<b>прив)</b>",
    "dunduk": "ты дундук? используй клавиатуру.",
    "kotik": "vot tebe kotik: \n\n\n ░░░▄▀▌░▄▀▌░░░░░░░░░░░░\n░▄██▀▀▀█▀▀▀▄╔╦╗╔╗╔╗╗╗╗\n▐███░▐░█░▐░█║║║╠╝║║║║║\n███████╥████╝╝╝╚╝╚╝╩╩╝\n█████╚═╩═╝██░░░░░░░░░░",
    "contacts": "по всем вопросам писать пока некуда.",
    "send_photo": "для загрузки треков отправь скрин, обрезанный!! файл не должен превышать 1Мб ! Размер до 1024х512",
    "save_success": "фоточка сохранена жди.......",
    "rec_success": "список треков: \n\n\n",
    "rec_success_end": "\n\nесли все верно нажми 'скачать!' \nесли все неверное нажми 'ошибка(' и попробуй еще раз!",
    "not_ready": "не готово сори...",
    "error": "попробуй еще раз((",
    "try_again": "попробуй отправить скрин с меньшим количеством треков и мусора: ",
    "wait_for_download": "жди загрузки...",
    "download_complete": "все треки отправлены.",
    "file_to_big": "файл не должен превышать 1Мб! \n ограничения на высоту 128 - 512 \n ограничения на ширину 128 - 1024 \n \n Ваши размеры: ",
    "track_error": "трек не найден или слишком длинный"

  },
  "buttons":
  {
    "main_menu": "менюшка",
    "contacts": "контактики",
    "send_photo": "прислать скрин",
    "send_kotik": "котик",
    "download": "скачать!",
    "error": "ошибка("
  }
}